setup.py
src/cyan/__init__.py
src/cyan.egg-info/PKG-INFO
src/cyan.egg-info/SOURCES.txt
src/cyan.egg-info/dependency_links.txt
src/cyan.egg-info/top_level.txt